setup.py
get_back_to_work_ronald/__init__.py
get_back_to_work_ronald.egg-info/PKG-INFO
get_back_to_work_ronald.egg-info/SOURCES.txt
get_back_to_work_ronald.egg-info/dependency_links.txt
get_back_to_work_ronald.egg-info/entry_points.txt
get_back_to_work_ronald.egg-info/requires.txt
get_back_to_work_ronald.egg-info/top_level.txt