Metadata-Version: 1.0
Name: get-back-to-work-ronald
Version: 0.1
Summary: Tell Ronald to get back to work
Home-page: https://github.com/AGhost-7/get-back-to-work-ronald
Author: Jonathan Boudreau
Author-email: jonathan.boudreau.92@gmail.com
License: UNKNOWN
Keywords: joke
Platform: UNKNOWN
